CHANGELOG.md
LICENSE
README.md
pygraph_tool/__init__.py
pygraph_tool/edge.py
pygraph_tool/graph.py
pygraph_tool/graph_exceptions.py
pygraph_tool/node.py
pygraph_tool-0.9.1.dist-info/LICENSE
pygraph_tool-0.9.1.dist-info/METADATA
pygraph_tool-0.9.1.dist-info/WHEEL
pygraph_tool-0.9.1.dist-info/RECORD
