Metadata-Version: 2.1
Name: pygraph-tool
Version: 0.9.1
Summary: pygraph-tool is a module to create and manipulate graphs.
Home-page: https://github.com/DevAI-64/pygraph-tool
License: MIT
Keywords: graph,pygraph,pygraph-tool,nodes,edges,node,edge
Author: BEL AICH David
Author-email: belaich.david@outlook.fr
Maintainer: BEL AICH David
Maintainer-email: belaich.david@outlook.fr
Requires-Python: >=3.8.1,<4.0.0
Classifier: Development Status :: 5 - Production/Stable
Classifier: License :: OSI Approved :: MIT License
Classifier: Programming Language :: Python :: 3
Classifier: Programming Language :: Python :: 3.9
Classifier: Programming Language :: Python :: 3.10
Classifier: Programming Language :: Python :: 3.11
Classifier: Programming Language :: Python :: 3
Classifier: Topic :: Scientific/Engineering
Project-URL: Repository, https://github.com/DevAI-64/pygraph-tool
